[
    {
        "type": "Directory",
        "name": "d:\\local_websites\\Goutu_Main\\wp-content\\plugins\\custom-batch-manage-posts",
        "parent_id": null,
        "fsPath": "d:\\local_websites\\Goutu_Main\\wp-content\\plugins\\custom-batch-manage-posts",
        "workspaceRoot": null,
        "workspacePath": null,
        "id": "mN4i3LBpYM0CThE8"
    },
    {
        "type": "Directory",
        "name": "d:\\local_websites\\Goutu_Main\\wp-content\\plugins\\custom-post-management",
        "parent_id": null,
        "fsPath": "d:\\local_websites\\Goutu_Main\\wp-content\\plugins\\custom-post-management",
        "workspaceRoot": null,
        "workspacePath": null,
        "id": "CJyxpgXjHi3L0Sqt"
    },
    {
        "type": "Directory",
        "name": "d:\\local_websites\\Goutu_Main\\wp-content\\plugins\\custom-recipe-management",
        "parent_id": null,
        "fsPath": "d:\\local_websites\\Goutu_Main\\wp-content\\plugins\\custom-recipe-management",
        "workspaceRoot": null,
        "workspacePath": null,
        "id": "yApZfdlab3gT5jim"
    },
    {
        "type": "Directory",
        "name": "d:\\local_websites\\Goutu_Main\\wp-content\\plugins\\custom-navigation-helpers",
        "parent_id": null,
        "fsPath": "d:\\local_websites\\Goutu_Main\\wp-content\\plugins\\custom-navigation-helpers",
        "workspaceRoot": null,
        "workspacePath": null,
        "id": "BS1XfepLk3PUAZig"
    },
    {
        "type": "Directory",
        "name": "d:\\local_websites\\Goutu_Main\\wp-content\\plugins\\wpcustom-category-image",
        "parent_id": null,
        "fsPath": "d:\\local_websites\\Goutu_Main\\wp-content\\plugins\\wpcustom-category-image",
        "workspaceRoot": null,
        "workspacePath": null,
        "id": "avyGHbWEn6BDojKC"
    },
    {
        "type": "Directory",
        "name": "d:\\local_websites\\Goutu_Main\\wp-content\\plugins\\custom-peepso-helpers",
        "parent_id": null,
        "fsPath": "d:\\local_websites\\Goutu_Main\\wp-content\\plugins\\custom-peepso-helpers",
        "workspaceRoot": null,
        "workspacePath": null,
        "id": "HVjmfXPduBGvhlx8"
    },
    {
        "type": "Directory",
        "name": "d:\\local_websites\\Goutu_Main\\wp-content\\plugins\\custom-site-notifications",
        "parent_id": null,
        "fsPath": "d:\\local_websites\\Goutu_Main\\wp-content\\plugins\\custom-site-notifications",
        "workspaceRoot": null,
        "workspacePath": null,
        "id": "l7WhXrZFJmwjPadu"
    },
    {
        "type": "Directory",
        "name": "d:\\local_websites\\Goutu_Main\\wp-content\\themes\\foodiepro-2.1.8",
        "parent_id": null,
        "fsPath": "d:\\local_websites\\Goutu_Main\\wp-content\\themes\\foodiepro-2.1.8",
        "workspaceRoot": null,
        "workspacePath": null,
        "id": "3lojXwPZuFc6hVz9"
    },
    {
        "type": "Directory",
        "name": "d:\\local_websites\\Goutu_Main\\wp-content\\plugins\\custom-star-rating",
        "parent_id": null,
        "fsPath": "d:\\local_websites\\Goutu_Main\\wp-content\\plugins\\custom-star-rating",
        "workspaceRoot": null,
        "workspacePath": null,
        "id": "yuWxincmkoXep4ON"
    }
]
